RTL/counter.v
module universal_counter
#(
    parameter WIDTH = 4
)
(
    input  wire                  clk,
    input  wire                  reset,
    input  wire                  enable,
    input  wire                  load,
    input  wire                  up_down,
    input  wire [WIDTH-1:0]      load_data,

    output reg  [WIDTH-1:0]      count,
    output reg                   overflow,
    output reg                   underflow,
    output wire                  terminal_count
);

assign terminal_count =
       (up_down) ? (count == {WIDTH{1'b1}})
                 : (count == {WIDTH{1'b0}});

always @(posedge clk)
begin

    overflow  <= 1'b0;
    underflow <= 1'b0;

    if(reset)
    begin
        count <= {WIDTH{1'b0}};
    end

    else if(load)
    begin
        count <= load_data;
    end

    else if(enable)
    begin

        if(up_down)
        begin

            if(count == {WIDTH{1'b1}})
            begin
                count <= {WIDTH{1'b0}};
                overflow <= 1'b1;
            end

            else
            begin
                count <= count + 1'b1;
            end

        end

        else
        begin

            if(count == {WIDTH{1'b0}})
            begin
                count <= {WIDTH{1'b1}};
                underflow <= 1'b1;
            end

            else
            begin
                count <= count - 1'b1;
            end

        end

    end

end

endmodule

RTL/counter_tb.v
`timescale 1ns/1ps

module counter_tb;

parameter WIDTH = 4;

reg clk;
reg reset;
reg enable;
reg load;
reg up_down;
reg [WIDTH-1:0] load_data;

wire [WIDTH-1:0] count;
wire overflow;
wire underflow;
wire terminal_count;

universal_counter #(
    .WIDTH(WIDTH)
) DUT (
    .clk(clk),
    .reset(reset),
    .enable(enable),
    .load(load),
    .up_down(up_down),
    .load_data(load_data),
    .count(count),
    .overflow(overflow),
    .underflow(underflow),
    .terminal_count(terminal_count)
);

// Clock Generation
initial begin
    clk = 0;
    forever #5 clk = ~clk;
end

// Monitor
initial begin
    $monitor("Time=%0t | Reset=%b Enable=%b Load=%b Up=%b LoadData=%d Count=%d Overflow=%b Underflow=%b TC=%b",
             $time, reset, enable, load, up_down, load_data,
             count, overflow, underflow, terminal_count);
end

// Stimulus
initial begin
$dumpfile("counter.vcd");
$dumpvars(0, counter_tb);
    reset = 1;
    enable = 0;
    load = 0;
    up_down = 1;
    load_data = 0;

    #20;

    reset = 0;

    // -----------------------
    // Test 1 : Up Counter
    // -----------------------
    enable = 1;
    up_down = 1;
    #80;

    // -----------------------
    // Test 2 : Load Value
    // -----------------------
    load = 1;
    load_data = 10;
    #10;
    load = 0;
    #50;

    // -----------------------
    // Test 3 : Down Counter
    // -----------------------
    up_down = 0;
    #120;

    // -----------------------
    // Test 4 : Disable Counter
    // -----------------------
    enable = 0;
    #30;

    // -----------------------
    // Test 5 : Enable Again
    // -----------------------
    enable = 1;
    up_down = 1;
    #80;

    $finish;

end

endmodule

Simulation/counter.vcd
$date
	Mon Jul 13 13:07:03 2026
$end
$version
	Icarus Verilog
$end
$timescale
	1ps
$end
$scope module counter_tb $end
$var wire 1 ! underflow $end
$var wire 1 " terminal_count $end
$var wire 1 # overflow $end
$var wire 4 $ count [3:0] $end
$var parameter 32 % WIDTH $end
$var reg 1 & clk $end
$var reg 1 ' enable $end
$var reg 1 ( load $end
$var reg 4 ) load_data [3:0] $end
$var reg 1 * reset $end
$var reg 1 + up_down $end
$scope module DUT $end
$var wire 1 & clk $end
$var wire 1 ' enable $end
$var wire 1 ( load $end
$var wire 4 , load_data [3:0] $end
$var wire 1 * reset $end
$var wire 1 + up_down $end
$var wire 1 " terminal_count $end
$var parameter 32 - WIDTH $end
$var reg 4 . count [3:0] $end
$var reg 1 # overflow $end
$var reg 1 ! underflow $end
$upscope $end
$upscope $end
$enddefinitions $end
$comment Show the parameter values. $end
$dumpall
b100 -
b100 %
$end
#0
$dumpvars
bx .
b0 ,
1+
1*
b0 )
0(
0'
0&
bx $
x#
x"
x!
$end
#5000
0"
b0 $
b0 .
0!
0#
1&
#10000
0&
#15000
1&
#20000
0&
1'
0*
#25000
b1 $
b1 .
1&
#30000
0&
#35000
b10 $
b10 .
1&
#40000
0&
#45000
b11 $
b11 .
1&
#50000
0&
#55000
b100 $
b100 .
1&
#60000
0&
#65000
b101 $
b101 .
1&
#70000
0&
#75000
b110 $
b110 .
1&
#80000
0&
#85000
b111 $
b111 .
1&
#90000
0&
#95000
b1000 $
b1000 .
1&
#100000
0&
b1010 )
b1010 ,
1(
#105000
b1010 $
b1010 .
1&
#110000
0&
0(
#115000
b1011 $
b1011 .
1&
#120000
0&
#125000
b1100 $
b1100 .
1&
#130000
0&
#135000
b1101 $
b1101 .
1&
#140000
0&
#145000
b1110 $
b1110 .
1&
#150000
0&
#155000
1"
b1111 $
b1111 .
1&
#160000
0"
0&
0+
#165000
b1110 $
b1110 .
1&
#170000
0&
#175000
b1101 $
b1101 .
1&
#180000
0&
#185000
b1100 $
b1100 .
1&
#190000
0&
#195000
b1011 $
b1011 .
1&
#200000
0&
#205000
b1010 $
b1010 .
1&
#210000
0&
#215000
b1001 $
b1001 .
1&
#220000
0&
#225000
b1000 $
b1000 .
1&
#230000
0&
#235000
b111 $
b111 .
1&
#240000
0&
#245000
b110 $
b110 .
1&
#250000
0&
#255000
b101 $
b101 .
1&
#260000
0&
#265000
b100 $
b100 .
1&
#270000
0&
#275000
b11 $
b11 .
1&
#280000
0&
0'
#285000
1&
#290000
0&
#295000
1&
#300000
0&
#305000
1&
#310000
0&
1+
1'
#315000
b100 $
b100 .
1&
#320000
0&
#325000
b101 $
b101 .
1&
#330000
0&
#335000
b110 $
b110 .
1&
#340000
0&
#345000
b111 $
b111 .
1&
#350000
0&
#355000
b1000 $
b1000 .
1&
#360000
0&
#365000
b1001 $
b1001 .
1&
#370000
0&
#375000
b1010 $
b1010 .
1&
#380000
0&
#385000
b1011 $
b1011 .
1&
